BPMN_RPA/__init__.py
BPMN_RPA/BPMN-RPA_PlugIn.js
BPMN_RPA/BPMN_RPA_Checklist_resume.py
BPMN_RPA/BPMN_RPA_Checklist_start.py
BPMN_RPA/BPMN_RPA_Starter.py
BPMN_RPA/CheckListEngine.py
BPMN_RPA/COPYING
BPMN_RPA/Generate_drawIO_library.py
BPMN_RPA/Images/add.png
BPMN_RPA/Images/BPMN_RPA_logo.PNG
BPMN_RPA/Images/delete.png
BPMN_RPA/Images/edit.png
BPMN_RPA/Images/error.png
BPMN_RPA/Images/Exit_not_ok.PNG
BPMN_RPA/Images/Get_input_parameter.PNG
BPMN_RPA/Images/Instantiate_class1.PNG
BPMN_RPA/Images/Instantiate_class2.PNG
BPMN_RPA/Images/Loop_example.PNG
BPMN_RPA/Images/loop_firstexecution.PNG
BPMN_RPA/Images/Looplist_attributes.PNG
BPMN_RPA/Images/Looptest_attributes.PNG
BPMN_RPA/Images/MessageBox_attributes.PNG
BPMN_RPA/Images/my_flow.png
BPMN_RPA/Images/ok.png
BPMN_RPA/Images/os_system.PNG
BPMN_RPA/Images/Reset_loopcounter.png
BPMN_RPA/Images/run.png
BPMN_RPA/Scripts/__init__.py
BPMN_RPA/Scripts/app.ico
BPMN_RPA/Scripts/base_config.cfg
BPMN_RPA/Scripts/Code.py
BPMN_RPA/Scripts/Compare.py
BPMN_RPA/Scripts/config.cfg
BPMN_RPA/Scripts/dev.spacy
BPMN_RPA/Scripts/Dialog.py
BPMN_RPA/Scripts/Excel.py
BPMN_RPA/Scripts/FTP.py
BPMN_RPA/Scripts/Images.py
BPMN_RPA/Scripts/Jira.py
BPMN_RPA/Scripts/Keepass.py
BPMN_RPA/Scripts/Keyboard.py
BPMN_RPA/Scripts/MessageBox.py
BPMN_RPA/Scripts/Mouse.py
BPMN_RPA/Scripts/Open_AI.py
BPMN_RPA/Scripts/Outlook.py
BPMN_RPA/Scripts/output/model-best/config.cfg
BPMN_RPA/Scripts/output/model-best/meta.json
BPMN_RPA/Scripts/output/model-best/textcat_multilabel/cfg
BPMN_RPA/Scripts/output/model-best/textcat_multilabel/model
BPMN_RPA/Scripts/output/model-best/tokenizer
BPMN_RPA/Scripts/output/model-best/vocab/key2row
BPMN_RPA/Scripts/output/model-best/vocab/lookups.bin
BPMN_RPA/Scripts/output/model-best/vocab/strings.json
BPMN_RPA/Scripts/output/model-best/vocab/vectors
BPMN_RPA/Scripts/output/model-best/vocab/vectors.cfg
BPMN_RPA/Scripts/output/model-last/config.cfg
BPMN_RPA/Scripts/output/model-last/meta.json
bpmn_rpa-9.2.5.dist-info/LICENSE
bpmn_rpa-9.2.5.dist-info/METADATA
bpmn_rpa-9.2.5.dist-info/WHEEL
bpmn_rpa-9.2.5.dist-info/RECORD
